pakto/__init__.py
pakto/cli/__init__.py
pakto/cli/context.py
pakto/cli/global_group.py
pakto/cli/main.py
pakto/cli/progress.py
pakto/commands/__init__.py
pakto/commands/bundle.py
pakto/commands/config.py
pakto/commands/init.py
pakto/commands/keys.py
pakto/commands/lock.py
pakto/commands/pack.py
pakto/commands/unpack.py
pakto/core/__init__.py
pakto/core/bundle.py
pakto/core/commands.py
pakto/core/config.py
pakto/core/constants.py
pakto/core/logging.py
pakto/core/models.py
pakto/core/oci_types.py
pakto/core/types.py
pakto/core/clients/__init__.py
pakto/core/clients/http.py
pakto/core/clients/oci_native.py
pakto/core/clients/registry.py
pakto/core/schemas/__init__.py
pakto/core/schemas/v1alpha1/__init__.py
pakto/core/schemas/v1alpha1/config.json
pakto/core/schemas/v1alpha1/lock.json
pakto/core/schemas/v1alpha1/manifest.json
pakto/handlers/__init__.py
pakto/handlers/base.py
pakto/handlers/factory.py
pakto/handlers/file.py
pakto/handlers/http.py
pakto/handlers/oci.py
pakto/handlers/pack.py
pakto/security/__init__.py
pakto/security/keys.py
pakto/security/utils.py
pakto/security/signer/__init__.py
pakto/security/signer/base.py
pakto/security/signer/key_based.py
pakto/services/__init__.py
pakto/services/config.py
pakto/services/lock.py
pakto/services/lockfile.py
pakto/services/manifest.py
pakto/services/pack.py
pakto/services/templating.py
pakto/services/unpack.py
pakto/services/validation.py
pakto/services/cache/__init__.py
pakto/services/cache/http_cache.py
pakto/services/cache/metadata.py
pakto/services/cache/resolver.py
pakto/services/cache/storage.py
pakto/utils/__init__.py
pakto/utils/decorators.py
pakto/utils/files.py
pakto-0.0.1a1.dist-info/METADATA
pakto-0.0.1a1.dist-info/WHEEL
pakto-0.0.1a1.dist-info/entry_points.txt
pakto-0.0.1a1.dist-info/licenses/LICENSE
pakto-0.0.1a1.dist-info/RECORD
