Metadata-Version: 2.4
Name: pakto
Version: 0.0.1a1
Summary: A CLI tool for bundling and distributing software as OCI artifacts with enterprise-grade security and compliance features
Project-URL: Homepage, https://github.com/wixregiga/pakto
Project-URL: Documentation, https://github.com/wixregiga/pakto#readme
Project-URL: Repository, https://github.com/wixregiga/pakto.git
Project-URL: Bug Tracker, https://github.com/wixregiga/pakto/issues
Project-URL: Source Code, https://github.com/wixregiga/pakto
Project-URL: Download, https://github.com/wixregiga/pakto/releases
Project-URL: Changelog, https://github.com/wixregiga/pakto/blob/main/CHANGELOG.md
Author-email: wixregiga <kecyojagi@protonmail.com>
Maintainer-email: wixregiga <kecyojagi@protonmail.com>
License: MIT
License-File: LICENSE
Keywords: airgapped,artifact,bundle,cli,compliance,container,containers,deployment,devops,distribution,enterprise,oci,offline,registry,sbom,security,software-bill-of-materials,software-distribution,templating,verification
Classifier: Development Status :: 3 - Alpha
Classifier: Environment :: Console
Classifier: Intended Audience :: Developers
Classifier: Intended Audience :: Information Technology
Classifier: Intended Audience :: System Administrators
Classifier: License :: OSI Approved :: MIT License
Classifier: Operating System :: OS Independent
Classifier: Programming Language :: Python :: 3
Classifier: Programming Language :: Python :: 3.9
Classifier: Programming Language :: Python :: 3.10
Classifier: Programming Language :: Python :: 3.11
Classifier: Programming Language :: Python :: 3.12
Classifier: Programming Language :: Python :: 3.13
Classifier: Topic :: Software Development :: Build Tools
Classifier: Topic :: Software Development :: Libraries :: Python Modules
Classifier: Topic :: System :: Software Distribution
Classifier: Topic :: System :: Systems Administration
Classifier: Topic :: Utilities
Classifier: Typing :: Typed
Requires-Python: >=3.9.5
Requires-Dist: aiofiles>=24.1.0
Requires-Dist: aiohttp>=3.12.7
Requires-Dist: aioresponses>=0.7.8
Requires-Dist: click==8.1.8
Requires-Dist: cryptography>=45.0.4
Requires-Dist: cyclonedx-python-lib>=10.3.0
Requires-Dist: docker-registry-client>=0.5.2
Requires-Dist: httpx>=0.28.1
Requires-Dist: jinja2>=3.1.6
Requires-Dist: jsonschema>=4.23.0
Requires-Dist: oras==0.2.35
Requires-Dist: packaging>=25.0
Requires-Dist: pydantic>=2.11.5
Requires-Dist: pyyaml>=6.0.2
Requires-Dist: repro-tarfile>=0.2.0
Requires-Dist: requests>=2.32.3
Requires-Dist: rich>=14.0.0
Requires-Dist: sigstore>=1.0.0
Provides-Extra: dev
Requires-Dist: ipdb>=0.13.13; extra == 'dev'
Requires-Dist: ipykernel>=6.29.5; extra == 'dev'
Requires-Dist: ipywidgets>=8.1.7; extra == 'dev'
Requires-Dist: marimo[recommended]>=0.14.6; extra == 'dev'
Requires-Dist: nest-asyncio>=1.6.0; extra == 'dev'
Requires-Dist: pdbpp>=0.11.6; extra == 'dev'
Requires-Dist: pytest-asyncio>=1.0.0; extra == 'dev'
Requires-Dist: pytest>=8.3.5; extra == 'dev'
Provides-Extra: docs
Requires-Dist: myst-parser>=2.0.0; extra == 'docs'
Requires-Dist: sphinx-rtd-theme>=2.0.0; extra == 'docs'
Requires-Dist: sphinx>=7.0.0; extra == 'docs'
Provides-Extra: test
Requires-Dist: nest-asyncio>=1.6.0; extra == 'test'
Requires-Dist: pytest-asyncio>=1.0.0; extra == 'test'
Requires-Dist: pytest>=8.3.5; extra == 'test'
